MANIFEST.in
setup.py
django_qshop.egg-info/PKG-INFO
django_qshop.egg-info/SOURCES.txt
django_qshop.egg-info/dependency_links.txt
django_qshop.egg-info/not-zip-safe
django_qshop.egg-info/top_level.txt
qshop/__init__.py
qshop/admin.py
qshop/admin_filters.py
qshop/admin_forms.py
qshop/classes.py
qshop/functions.py
qshop/mails.py
qshop/middleware.py
qshop/models.py
qshop/qshop_settings.py
qshop/thumbnail_processors.py
qshop/translation.py
qshop/urls.py
qshop/views.py
qshop/cart/__init__.py
qshop/cart/admin.py
qshop/cart/cart.py
qshop/cart/forms.py
qshop/cart/models.py
qshop/cart/overloadable_functions.py
qshop/cart/urls.py
qshop/cart/views.py
qshop/locale/lv/LC_MESSAGES/django.mo
qshop/locale/lv/LC_MESSAGES/django.po
qshop/locale/ru/LC_MESSAGES/django.mo
qshop/locale/ru/LC_MESSAGES/django.po
qshop/payment_vendors/__init__.py
qshop/payment_vendors/payment.py
qshop/payment_vendors/urls.py
qshop/payment_vendors/views.py
qshop/payment_vendors/banktransfer/__init__.py
qshop/payment_vendors/banktransfer/banktransfer.py
qshop/payment_vendors/paypal/__init__.py
qshop/payment_vendors/paypal/paypal.py
qshop/payment_vendors/webmoney/__init__.py
qshop/payment_vendors/webmoney/webmoney.py
qshop/static/admin/qshop/css/products.css
qshop/static/admin/qshop/js/products.js
qshop/static/admin/qshop/js/products_parametervalues.js
qshop/templates/qshop/productpage.html
qshop/templates/qshop/productspage.html
qshop/templates/qshop/shoppage.html
qshop/templates/qshop/admin/actions/change_price.html
qshop/templates/qshop/admin/actions/link_to_category.html
qshop/templates/qshop/admin/actions/set_discount.html
qshop/templates/qshop/admin/actions/unlink_from_category.html
qshop/templates/qshop/cart/_cart_as_table.html
qshop/templates/qshop/cart/cart.html
qshop/templates/qshop/cart/order.html
qshop/templates/qshop/cart/order_cancelled.html
qshop/templates/qshop/cart/order_error.html
qshop/templates/qshop/cart/order_success.html
qshop/templates/qshop/mails/order_sended.html
qshop/templates/qshop/payment_vendors/redirect_with_post.html
qshop/templatetags/__init__.py
qshop/templatetags/qshop.py