Metadata-Version: 1.1
Name: django-qshop
Version: 0.2.0
Summary: E-commerce for django. Requires django-sitemenu. Beta version.
Home-page: https://github.com/Brick85/django-qshop
Author: Vital Belikov
Author-email: vital@qwe.lv
License: New BSD
Platform: UNKNOWN
Classifier: Development Status :: 4 - Beta
Classifier: Environment :: Web Environment
Classifier: Framework :: Django
Classifier: Intended Audience :: Developers
Classifier: License :: OSI Approved :: BSD License
Classifier: Natural Language :: English
Classifier: Operating System :: Unix
Classifier: Programming Language :: Python :: 2.7
Classifier: Topic :: Utilities
Requires: django(>=1.4)
Requires: django_sitemenu
Requires: easy_thumbnails
